.gitignore
LICENSE
MANIFEST.in
README.txt
appeus.theme-configure.zcml
ignore.txt
setup.cfg
setup.py
appeus/__init__.py
appeus.theme.egg-info/PKG-INFO
appeus.theme.egg-info/SOURCES.txt
appeus.theme.egg-info/dependency_links.txt
appeus.theme.egg-info/entry_points.txt
appeus.theme.egg-info/namespace_packages.txt
appeus.theme.egg-info/not-zip-safe
appeus.theme.egg-info/requires.txt
appeus.theme.egg-info/top_level.txt
appeus/theme/__init__.py
appeus/theme/configure.zcml
appeus/theme/profiles.zcml
appeus/theme/rebuild_i18n.sh
appeus/theme/setuphandlers.py
appeus/theme/skins.zcml
appeus/theme/tests.py
appeus/theme/browser/__init__.py
appeus/theme/browser/configure.zcml
appeus/theme/browser/controlpanel.py
appeus/theme/browser/home.py
appeus/theme/browser/interfaces.py
appeus/theme/browser/resources/stylesheets/view.css
appeus/theme/browser/template-overrides/CONTENTS.txt
appeus/theme/browser/template-overrides/eea.facetednavigation.browser.stylesheets.view.css
appeus/theme/browser/template-overrides/eea.facetednavigation.browser.template.widgets.pt
appeus/theme/browser/template-overrides/eea.facetednavigation.views.preview-items.pt
appeus/theme/browser/template-overrides/plone.app.contenttypes.browser.templates.newsitem.pt
appeus/theme/browser/template-overrides/plone.app.contenttypes.browser.templates.standard_view.pt
appeus/theme/browser/template-overrides/plone.app.contenttypes.browser.templates.summary_view.pt
appeus/theme/browser/template-overrides/plone.app.discussion.browser.comments.pt
appeus/theme/browser/template-overrides/plone.app.layout.viewlets.document_byline.pt
appeus/theme/browser/template-overrides/plone.app.layout.viewlets.keywords.pt
appeus/theme/browser/template-overrides/plone.app.layout.viewlets.path_bar.pt
appeus/theme/browser/template-overrides/plone.app.layout.viewlets.searchbox.pt
appeus/theme/browser/templates/CONTENTS.txt
appeus/theme/browser/templates/batchnavigation_bootstrap.pt
appeus/theme/browser/templates/home.pt
appeus/theme/locales/appeus.theme-manual.pot
appeus/theme/locales/appeus.theme.pot
appeus/theme/locales/plone.pot
appeus/theme/locales/eu/LC_MESSAGES/appeus.theme.mo
appeus/theme/locales/eu/LC_MESSAGES/appeus.theme.po
appeus/theme/locales/eu/LC_MESSAGES/plone.mo
appeus/theme/locales/eu/LC_MESSAGES/plone.po
