Metadata-Version: 1.1
Name: appeus.theme
Version: 1.3.1
Summary: Installable theme: appeus.theme
Home-page: https://bitbucket.org/codesyntax/appeus.theme/
Author: Mikel Larreategi
Author-email: mlarreategi@codesyntax.com
License: GPL
Platform: UNKNOWN
Classifier: Framework :: Plone
Classifier: Programming Language :: Python
